llamapy/__init__.py
llamapy/llamapy.py
llamapy-0.0.2.dist-info/LICENSE
llamapy-0.0.2.dist-info/METADATA
llamapy-0.0.2.dist-info/WHEEL
llamapy-0.0.2.dist-info/top_level.txt
llamapy-0.0.2.dist-info/RECORD
