Metadata-Version: 2.1
Name: llamapy
Version: 0.0.2
Summary: A package to make interfacing between Airpy and Google Sheets easier
Home-page: https://git.musta.ch/alex-shannon/llamapy
Author: Alex Shannon
Author-email: alex.shannon@airbnb.com
License: UNKNOWN
Platform: UNKNOWN
Classifier: Programming Language :: Python :: 3
Classifier: License :: OSI Approved :: MIT License
Classifier: Operating System :: OS Independent
Requires-Python: >=3.6
Requires-Dist: gspread
